README.rst
setup.py
macroeco/__init__.py
macroeco.egg-info/PKG-INFO
macroeco.egg-info/SOURCES.txt
macroeco.egg-info/dependency_links.txt
macroeco.egg-info/requires.txt
macroeco.egg-info/top_level.txt
macroeco/compare/__init__.py
macroeco/compare/_compare.py
macroeco/compare/test_compare.py
macroeco/empirical/__init__.py
macroeco/empirical/_empirical.py
macroeco/empirical/test_empirical.py
macroeco/empirical/test_meta1.txt
macroeco/empirical/test_meta2.txt
macroeco/empirical/test_table1.csv
macroeco/empirical/test_table2.csv
macroeco/main/__init__.py
macroeco/main/_gui.py
macroeco/main/_main.py
macroeco/misc/__init__.py
macroeco/misc/format_data.py
macroeco/misc/misc.py
macroeco/misc/rcparams.py
macroeco/misc/test_format_data.py
macroeco/models/__init__.py
macroeco/models/_curves.py
macroeco/models/_distributions.py
macroeco/models/_distributions_docstrings.py
macroeco/models/test_curves.py
macroeco/models/test_distributions.py