Metadata-Version: 1.1
Name: macroeco
Version: 1.0
Summary: Ecological pattern analysis in Python
Home-page: http://github.com/jkitzes/macroeco
Author: Justin Kitzes and Mark Wilber
Author-email: jkitzes@berkeley.edu
License: BSD
Keywords: ecology macroecology biology environment biodiversity informatics data science
Platform: UNKNOWN
Classifier: Topic :: Scientific/Engineering :: Bio-Informatics
Classifier: Development Status :: 4 - Beta
Classifier: Intended Audience :: Science/Research
Classifier: License :: OSI Approved :: BSD License
